aine_drl/__init__.py
aine_drl/env.py
aine_drl/exp.py
aine_drl/factory.py
aine_drl/net.py
aine_drl/policy.py
aine_drl/policy_dist.py
aine_drl/rl_loss.py
aine_drl/agent/__init__.py
aine_drl/agent/agent.py
aine_drl/agent/a2c/__init__.py
aine_drl/agent/a2c/a2c.py
aine_drl/agent/a2c/config.py
aine_drl/agent/a2c/net.py
aine_drl/agent/a2c/trajectory.py
aine_drl/agent/dqn/__init__.py
aine_drl/agent/dqn/config.py
aine_drl/agent/dqn/double_dqn.py
aine_drl/agent/dqn/net.py
aine_drl/agent/dqn/trajectory.py
aine_drl/agent/ppo/__init__.py
aine_drl/agent/ppo/config.py
aine_drl/agent/ppo/net.py
aine_drl/agent/ppo/ppo.py
aine_drl/agent/ppo/ppo_rnd.py
aine_drl/agent/ppo/recurrent_ppo.py
aine_drl/agent/ppo/recurrent_ppo_rnd.py
aine_drl/agent/ppo/trajectory.py
aine_drl/agent/reinforce/__init__.py
aine_drl/agent/reinforce/config.py
aine_drl/agent/reinforce/net.py
aine_drl/agent/reinforce/reinforce.py
aine_drl/agent/reinforce/trajectory.py
aine_drl/run/__init__.py
aine_drl/run/error.py
aine_drl/run/inference.py
aine_drl/run/train.py
aine_drl/util/__init__.py
aine_drl/util/decay.py
aine_drl/util/func.py
aine_drl/util/incremental_calc.py
aine_drl/util/logger.py
aine_drl/util/truncated_seq_gen.py
aine_drl-0.1.1.dist-info/LICENSE
aine_drl-0.1.1.dist-info/METADATA
aine_drl-0.1.1.dist-info/WHEEL
aine_drl-0.1.1.dist-info/top_level.txt
aine_drl-0.1.1.dist-info/RECORD
