Metadata-Version: 2.1
Name: aine-drl
Version: 0.1.1
Summary: AINE-DRL is a deep reinforcement learning (DRL) baseline framework. AINE means "Agent IN Environment".
Home-page: https://github.com/DevSlem/AINE-DRL
Author: DevSlem
Author-email: devslem12@gmail.com
License: MIT
Keywords: deep reinforcement learning,reinforcement learning,drl,deep learning,rl,game,ppo,gym,mlagents,pytorch
Requires-Python: >=3.9
License-File: LICENSE
Requires-Dist: torch (==1.11.0)
Requires-Dist: tensorboard (==2.12.0)
Requires-Dist: PyYAML (==6.0)
Requires-Dist: gym (==0.26.2)
Requires-Dist: gym[all]
Requires-Dist: mlagents (==0.30.0)
Requires-Dist: protobuf (==3.20.3)
